{
    "manufacturer": "Redmi",
    "models": [
    {
        "__id__": "1Fa7fi43zcin51cdkW0J",
        "collimator": 90,
        "device_name": "Redmi Note 8A",
        "dpi": 659,
        "fire_button": 40,
        "free_review": 35,
        "review": 97,
        "settings_source_url": "",
        "sniper_scope": 25,
        "x2_scope": 100,
        "x4_scope": 97
    },
    {
        "__id__": "1y2yDCsJEdbQ1Gni4xDm",
        "collimator": 93,
        "device_name": "Redmi 10C",
        "dpi": 0,
        "fire_button": 45,
        "free_review": 46,
        "review": 93,
        "settings_source_url": "",
        "sniper_scope": 22,
        "x2_scope": 94,
        "x4_scope": 92
    },
    {
        "__id__": "3nDEyyZM6eb3DtBUQgoF",
        "collimator": 97,
        "device_name": "Redmi 9 NFC",
        "dpi": 430,
        "fire_button": 48,
        "free_review": 47,
        "review": 95,
        "settings_source_url": "https://www.tiktok.com/@777_honour_777/video/7108353009192619269?is_from_webapp=1&sender_device=pc&web_id=7109889579923113478",
        "sniper_scope": 54,
        "x2_scope": 92,
        "x4_scope": 92
    },
    {
        "__id__": "75E97BExoPEYaVj00G90",
        "collimator": 96,
        "device_name": "Redmi Note 10 Pro",
        "dpi": 553,
        "fire_button": 50,
        "free_review": 32,
        "review": 95,
        "settings_source_url": "https://www.tiktok.com/@777_honour_777/video/7108029498716720389?is_from_webapp=1&sender_device=pc&web_id=7109889579923113478",
        "sniper_scope": 60,
        "x2_scope": 91,
        "x4_scope": 100
    },
    {
        "__id__": "7uF7uLvk9vO3aX9x6NMs",
        "collimator": 97,
        "device_name": "Redmi Note 5",
        "dpi": 551,
        "fire_button": 43,
        "free_review": 54,
        "review": 98,
        "settings_source_url": "",
        "sniper_scope": 46,
        "x2_scope": 99,
        "x4_scope": 95
    },
    {
        "__id__": "ADej1RTYA1RyX3PhKRC2",
        "collimator": 93,
        "device_name": "Redmi Note 10s",
        "dpi": 535,
        "fire_button": 52,
        "free_review": 50,
        "review": 96,
        "settings_source_url": "",
        "sniper_scope": 60,
        "x2_scope": 96,
        "x4_scope": 91
    },
    {
        "__id__": "DGtFQmHzoFvFFTLZKeLb",
        "collimator": 93,
        "device_name": "Redmi Note 9 Pro",
        "dpi": 619,
        "fire_button": 41,
        "free_review": 100,
        "review": 97,
        "settings_source_url": "https://www.tiktok.com/@777_honour_777/video/7119490738747968773?is_from_webapp=1&sender_device=pc&web_id=7109889579923113478",
        "sniper_scope": 45,
        "x2_scope": 100,
        "x4_scope": 100
    },
    {
        "__id__": "HyWWx4XhxxH2Met6orIP",
        "collimator": 94,
        "device_name": "Redmi 10S",
        "dpi": 0,
        "fire_button": 43,
        "free_review": 50,
        "review": 93,
        "settings_source_url": "",
        "sniper_scope": 20,
        "x2_scope": 100,
        "x4_scope": 93
    },
    {
        "__id__": "LfYkDGMT9YC7kXrCkpQL",
        "collimator": 90,
        "device_name": "Redmi 10A",
        "dpi": 0,
        "fire_button": 47,
        "free_review": 45,
        "review": 98,
        "settings_source_url": "",
        "sniper_scope": 36,
        "x2_scope": 98,
        "x4_scope": 90
    },
    {
        "__id__": "LpglSR0JZPDoBkuIjGhl",
        "collimator": 94,
        "device_name": "Redmi 9t",
        "dpi": 615,
        "fire_button": 43,
        "free_review": 52,
        "review": 97,
        "settings_source_url": "",
        "sniper_scope": 55,
        "x2_scope": 96,
        "x4_scope": 95
    },
    {
        "__id__": "MPpzjh3s1qGX7MtQSAYf",
        "collimator": 91,
        "device_name": "Redmi Note 11 Pro",
        "dpi": 0,
        "fire_button": 40,
        "free_review": 30,
        "review": 98,
        "settings_source_url": "",
        "sniper_scope": 56,
        "x2_scope": 97,
        "x4_scope": 91
    },
    {
        "__id__": "NtyCIyBZuwC5UHAW85i4",
        "collimator": 100,
        "device_name": "Redmi 9A",
        "dpi": 720,
        "fire_button": 53,
        "free_review": 50,
        "review": 100,
        "settings_source_url": "https://vm.tiktok.com/ZMNt4MXko/",
        "sniper_scope": 50,
        "x2_scope": 100,
        "x4_scope": 100
    },
    {
        "__id__": "Pvty4WdM5WWqZ7bcJ8rZ",
        "collimator": 98,
        "device_name": "Redmi Note 9",
        "dpi": 570,
        "fire_button": 41,
        "free_review": 35,
        "review": 95,
        "settings_source_url": "",
        "sniper_scope": 41,
        "x2_scope": 93,
        "x4_scope": 100
    },
    {
        "__id__": "SZjhgRQuCqhVDWw5BFcJ",
        "collimator": 98,
        "device_name": "Redmi Note 11 Pro 5G",
        "dpi": 0,
        "fire_button": 40,
        "free_review": 39,
        "review": 93,
        "settings_source_url": "",
        "sniper_scope": 49,
        "x2_scope": 98,
        "x4_scope": 100
    },
    {
        "__id__": "UIpPbjME6ex5Itih96g2",
        "collimator": 100,
        "device_name": "Redmi 9C",
        "dpi": 730,
        "fire_button": 53,
        "free_review": 50,
        "review": 100,
        "settings_source_url": "https://vm.tiktok.com/ZMNt4MXko/",
        "sniper_scope": 50,
        "x2_scope": 100,
        "x4_scope": 100
    },
    {
        "__id__": "XAbPGBgUMa4VSp82G06k",
        "collimator": 93,
        "device_name": "Redmi 10",
        "dpi": 0,
        "fire_button": 45,
        "free_review": 40,
        "review": 97,
        "settings_source_url": "",
        "sniper_scope": 59,
        "x2_scope": 95,
        "x4_scope": 91
    },
    {
        "__id__": "XfgWjju5LJEp9RQwYfjb",
        "collimator": 97,
        "device_name": "Redmi Note 7",
        "dpi": 536,
        "fire_button": 45,
        "free_review": 53,
        "review": 98,
        "settings_source_url": "",
        "sniper_scope": 96,
        "x2_scope": 97,
        "x4_scope": 97
    },
    {
        "__id__": "ZcXJtgw4uQFcE4jTYsXw",
        "collimator": 100,
        "device_name": "Redmi 7",
        "dpi": 420,
        "fire_button": 55,
        "free_review": 50,
        "review": 100,
        "settings_source_url": "https://vm.tiktok.com/ZMNt4rJh1/",
        "sniper_scope": 50,
        "x2_scope": 100,
        "x4_scope": 100
    },
    {
        "__id__": "bRu4sYBbvwRoYv2fmKIY",
        "collimator": 92,
        "device_name": "Redmi 9C NFC",
        "dpi": 731,
        "fire_button": 48,
        "free_review": 52,
        "review": 95,
        "settings_source_url": "",
        "sniper_scope": 21,
        "x2_scope": 93,
        "x4_scope": 93
    },
    {
        "__id__": "dGiuqHmW9QyqjQ9PpU2Z",
        "collimator": 88,
        "device_name": "Redmi 6 Pro",
        "dpi": 0,
        "fire_button": 43,
        "free_review": 34,
        "review": 95,
        "settings_source_url": "",
        "sniper_scope": 28,
        "x2_scope": 95,
        "x4_scope": 95
    },
    {
        "__id__": "fIzGcS1cFWB9rT6kaC7s",
        "collimator": 100,
        "device_name": "Redmi 8",
        "dpi": 540,
        "fire_button": 57,
        "free_review": 100,
        "review": 95,
        "settings_source_url": "https://www.tiktok.com/@777_honour_777/video/7123924103068798214?is_from_webapp=1&sender_device=pc&web_id=7109889579923113478",
        "sniper_scope": 100,
        "x2_scope": 100,
        "x4_scope": 100
    },
    {
        "__id__": "fthPvLlKx9gifMN4EdUV",
        "collimator": 91,
        "device_name": "Redmi Note 4",
        "dpi": 0,
        "fire_button": 42,
        "free_review": 100,
        "review": 99,
        "settings_source_url": "https://www.tiktok.com/@777_honour_777/video/7118534417764683013?is_from_webapp=1&sender_device=pc&web_id=7109889579923113478",
        "sniper_scope": 38,
        "x2_scope": 96,
        "x4_scope": 97
    },
    {
        "__id__": "heiozC3Kynh7xMbuqwKc",
        "collimator": 95,
        "device_name": "Redmi 6",
        "dpi": 0,
        "fire_button": 39,
        "free_review": 42,
        "review": 94,
        "settings_source_url": "",
        "sniper_scope": 20,
        "x2_scope": 93,
        "x4_scope": 94
    },
    {
        "__id__": "i4H3gTuIjkg5ZkjmpH9M",
        "collimator": 93,
        "device_name": "Redmi Note 6 Pro",
        "dpi": 470,
        "fire_button": 44,
        "free_review": 37,
        "review": 98,
        "settings_source_url": "",
        "sniper_scope": 27,
        "x2_scope": 94,
        "x4_scope": 94
    },
    {
        "__id__": "iNGuSeN1ruHPUlD88quz",
        "collimator": 97,
        "device_name": "Redmi 8 Pro",
        "dpi": 540,
        "fire_button": 48,
        "free_review": 100,
        "review": 100,
        "settings_source_url": "https://www.tiktok.com/@777_honour_777/video/7119277761180519686?is_from_webapp=1&sender_device=pc&web_id=7109889579923113478",
        "sniper_scope": 80,
        "x2_scope": 94,
        "x4_scope": 88
    },
    {
        "__id__": "o7Lrh84hsbXNXGNFk2O1",
        "collimator": 93,
        "device_name": "Redmi Note 8",
        "dpi": 600,
        "fire_button": 44,
        "free_review": 48,
        "review": 94,
        "settings_source_url": "",
        "sniper_scope": 24,
        "x2_scope": 94,
        "x4_scope": 95
    },
    {
        "__id__": "r5rGtwQ5velLfonnlFFS",
        "collimator": 94,
        "device_name": "Redmi 6A",
        "dpi": 0,
        "fire_button": 39,
        "free_review": 52,
        "review": 98,
        "settings_source_url": "",
        "sniper_scope": 36,
        "x2_scope": 90,
        "x4_scope": 96
    },
    {
        "__id__": "tgmbQwOuiw3AKQcRc62U",
        "collimator": 96,
        "device_name": "Redmi Note 9s",
        "dpi": 531,
        "fire_button": 53,
        "free_review": 49,
        "review": 95,
        "settings_source_url": "",
        "sniper_scope": 33,
        "x2_scope": 93,
        "x4_scope": 98
    },
    {
        "__id__": "vcIR3ehMXeK72jU7HRz0",
        "collimator": 88,
        "device_name": "Redmi Note 8 Pro",
        "dpi": 560,
        "fire_button": 42,
        "free_review": 45,
        "review": 94,
        "settings_source_url": "",
        "sniper_scope": 49,
        "x2_scope": 97,
        "x4_scope": 97
    },
    {
        "__id__": "wv5mMubgM45vyZRh6OF6",
        "collimator": 91,
        "device_name": "Redmi S2",
        "dpi": 614,
        "fire_button": 45,
        "free_review": 32,
        "review": 93,
        "settings_source_url": "",
        "sniper_scope": 26,
        "x2_scope": 96,
        "x4_scope": 93
    },
    {
        "__id__": "yRn8bVAezx2eOn6IvLVm",
        "collimator": 88,
        "device_name": "Redmi Note 11",
        "dpi": 0,
        "fire_button": 47,
        "free_review": 36,
        "review": 97,
        "settings_source_url": "",
        "sniper_scope": 21,
        "x2_scope": 99,
        "x4_scope": 97
    },
    {
        "__id__": "yigT025TpoV7KXaBf0f5",
        "collimator": 55,
        "device_name": "Redmi 9",
        "dpi": 720,
        "fire_button": 70,
        "free_review": 100,
        "review": 95,
        "settings_source_url": "https://www.tiktok.com/@ipman.pvp/video/7125938633269415173",
        "sniper_scope": 51,
        "x2_scope": 70,
        "x4_scope": 76
    },
    {
        "__id__": "ztqq7qWAhIuRjzCpEg0V",
        "collimator": 95,
        "device_name": "Redmi A8",
        "dpi": 639,
        "fire_button": 53,
        "free_review": 44,
        "review": 93,
        "settings_source_url": "",
        "sniper_scope": 18,
        "x2_scope": 96,
        "x4_scope": 91
    }
]
}